quick_image/__init__.py
quick_image/image_point_picker.py
quick_image/quick_image.py
quick_image/quick_image_processing.py
quick_image/quick_image_similarity_measures.py
quick_image/__pycache__/__init__.cpython-39.pyc
quick_image/__pycache__/image_point_picker.cpython-39.pyc
quick_image/__pycache__/quick_image.cpython-39.pyc
quick_image/__pycache__/quick_image_processing.cpython-39.pyc
quick_image/__pycache__/quick_image_similarity_measures.cpython-39.pyc
quick_image-0.0.1a0.dist-info/LICENSE
quick_image-0.0.1a0.dist-info/METADATA
quick_image-0.0.1a0.dist-info/WHEEL
quick_image-0.0.1a0.dist-info/top_level.txt
quick_image-0.0.1a0.dist-info/RECORD
